Metadata-Version: 2.1
Name: pypolish
Version: 0.0.7
Summary: Easily Polish Structured Data
Home-page: 
Author: Hunter Thomas
Author-email: waidai2027@gmail.com
License: MIT
Keywords: Polish data
Classifier: Development Status :: 5 - Production/Stable
Classifier: Intended Audience :: Education
Classifier: Operating System :: Microsoft :: Windows :: Windows 10
Classifier: License :: OSI Approved :: MIT License
Classifier: Programming Language :: Python :: 3
License-File: LICENSE
